aox/__init__.py
aox/version.py
aox/boilerplate/__init__.py
aox/boilerplate/base_boilerplate.py
aox/boilerplate/boilerplates/__init__.py
aox/boilerplate/boilerplates/default_boilerplate.py
aox/boilerplate/boilerplates/default_boilerplate_example_year/__init__.py
aox/boilerplate/boilerplates/default_boilerplate_example_year/example_day/__init__.py
aox/boilerplate/boilerplates/default_boilerplate_example_year/example_day/example_part.py
aox/challenge/__init__.py
aox/challenge/base_challenge.py
aox/challenge/debugging.py
aox/command_line/__init__.py
aox/command_line/command.py
aox/controller/__init__.py
aox/controller/controller.py
aox/model/__init__.py
aox/model/account_info.py
aox/model/combined_info.py
aox/model/repo_info.py
aox/settings/__init__.py
aox/settings/settings_class.py
aox/settings/settings_proxy_class.py
aox/settings/warnings.py
aox/styling/__init__.py
aox/styling/shortcuts.py
aox/summary/__init__.py
aox/summary/base_summary.py
aox/summary/summaries/__init__.py
aox/summary/summaries/event_summary.py
aox/summary/summaries/submissions_summary.py
aox/testing/__init__.py
aox/testing/doctest_enhanced_testmod.py
aox/testing/doctest_filter_parsing.py
aox/testing/doctest_filtering.py
aox/utils/__init__.py
aox/utils/ascii_formatting.py
aox/utils/backports.py
aox/utils/collections_utils.py
aox/utils/enums.py
aox/utils/functions.py
aox/utils/module_utils.py
aox/utils/paths.py
aox/utils/strings.py
aox/utils/timing.py
aox/utils/typing_utils.py
aox/web/__init__.py
aox/web/account.py
aox/web/aoc.py
aox-1.1.1.data/scripts/aox
aox-1.1.1.dist-info/LICENCE
aox-1.1.1.dist-info/METADATA
aox-1.1.1.dist-info/WHEEL
aox-1.1.1.dist-info/top_level.txt
aox-1.1.1.dist-info/RECORD
