Metadata-Version: 2.1
Name: aox
Version: 1.1.1
Summary: AdventOfCode Submissions Framework
Home-page: https://github.com/costas-basdekis/aox
Author: Costas Basdekis
Author-email: costas@basdekis.io
License: MIT License
Platform: UNKNOWN
Classifier: Development Status :: 5 - Production/Stable
Classifier: Environment :: Console
Classifier: Intended Audience :: Developers
Classifier: Intended Audience :: Education
Classifier: License :: OSI Approved :: MIT License
Classifier: Natural Language :: English
Classifier: Programming Language :: Python :: 3
Classifier: Programming Language :: Python :: 3.7
Classifier: Programming Language :: Python :: 3.8
Classifier: Programming Language :: Python :: 3.9
Classifier: Topic :: Software Development
Classifier: Typing :: Typed
License-File: LICENCE
